<?xml version="1.0" encoding="UTF-8"?>
<entity_web_browser>
  <entities>
    <web_browser id="Safari">
      <name>Safari</name>
    </web_browser>
    <web_browser id="Firefox_2_x">
      <name>Firefox 2.x</name>
    </web_browser>
    <web_browser id="Firefox_3_x">
      <name>Firefox 3.x</name>
    </web_browser>
    <web_browser id="Opera">
      <name>Opera</name>
    </web_browser>
    <web_browser id="IE_6_x">
      <name>IE 6.x</name>
    </web_browser>
    <web_browser id="IE_7_x">
      <name>IE 7.x</name>
    </web_browser>
    <web_browser id="IE_8_x">
      <name>IE 8.x</name>
    </web_browser>
    <web_browser id="Google_Chrome">
      <name>Google Chrome</name>
    </web_browser>
  </entities>
  <fields id="name">
    <field name="name"/>
  </fields>
</entity_web_browser>
